<?xml version="1.0" encoding="utf-8"?>
<mdRecord xmlns:dc="http://purl.org/dc/elements/1.1/"
          xmlns:dcterms="http://purl.org/dc/terms/"
          xmlns:rdf="http://www.w3.org/1999/02/22-rdf-syntax-ns#"
          xmlns:edm="http://www.europeana.eu/schemas/edm/"
          xmlns="http://dplava.lib.virginia.edu"
          xmlns:xsi="http://www.w3.org/2001/XMLSchema-instance"
          xsi:schemaLocation="http://dplava.lib.virginia.edu dplava.xsd">
   <dcterms:identifier>10010678</dcterms:identifier>
   <dcterms:title>The Bridge, Vol. 1, No. 11</dcterms:title>
   <dcterms:description>The Bridge, Vol. 1, No. 11 / "Our group held an historic meeting on November 10, 1964, in the Parent's and Friends' Lounge at Hampden-Sydney, Mr. Field led a devotional and presided over the meeting, whose purpose was to decide whether we should become the Prince Edward Chapter of the Virginia Council of Human Relations. During the discussion, all favored the proposal; in the voting that followed, there was not a single dissenting vote. The unanimous decision to form a Human Relations Council here shows the enthusiasm with which we enter upon this new path." / Individuals referenced: Mr. Field</dcterms:description>
   <dcterms:language>English</dcterms:language>
   <dcterms:creator>Unknown</dcterms:creator>
   <dcterms:subject>United States--Race Relations</dcterms:subject>
   <dcterms:subject>Civil Rights Movements--United States</dcterms:subject>
   <dcterms:subject>School Integration--Massive Resistance Movement--Southern States</dcterms:subject>
   <dcterms:subject>Prince Edward County Free School Association (Va.)</dcterms:subject>
   <dcterms:subject>Prince Edward County (Va.)</dcterms:subject>
   <dcterms:spatial>Prince Edward County School Closures</dcterms:spatial>
   <dcterms:date>1964-11</dcterms:date>
   <dcterms:type>Text</dcterms:type>
   <dcterms:isPartOf>College Church Biracial Study Group</dcterms:isPartOf>
   <dcterms:rights>http://rightsstatements.org/vocab/UND/1.0/</dcterms:rights>
   <dcterms:provenance>Hampden-Sydney College Archives &amp; Special Collections</dcterms:provenance>
   <edm:preview>http://dams.hsc.edu/files/original/4a2096af139165bf56e17508931b556c.jpg</edm:preview>
   <edm:isShownAt>http://dams.hsc.edu/items/show/912</edm:isShownAt>
</mdRecord>
